README.md
setup.py
covidcountydata/__init__.py
covidcountydata/client.py
covidcountydata/examples.py
covidcountydata/utils.py
covidcountydata.egg-info/PKG-INFO
covidcountydata.egg-info/SOURCES.txt
covidcountydata.egg-info/dependency_links.txt
covidcountydata.egg-info/requires.txt
covidcountydata.egg-info/top_level.txt