Metadata-Version: 2.1
Name: covidcountydata
Version: 0.4.0
Summary: Python client for accessing the COVID County Data database
Home-page: https://github.com/CovidCountyData/covidcountydata.py
Author: Valorum Data
Author-email: info@valorumdata.com
License: UNKNOWN
Project-URL: Bug Reports, https://github.com/CovidCountyData/covidcountydata.py/issues
Project-URL: Source, https://github.com/CovidCountyData/covidcountydata.py
Platform: UNKNOWN
Classifier: Development Status :: 3 - Alpha
Classifier: Intended Audience :: Developers
Classifier: Topic :: Software Development :: Build Tools
Classifier: License :: OSI Approved :: MIT License
Classifier: Programming Language :: Python :: 3
Classifier: Programming Language :: Python :: 3.5
Classifier: Programming Language :: Python :: 3.6
Classifier: Programming Language :: Python :: 3.7
Classifier: Programming Language :: Python :: 3.8
Classifier: Programming Language :: Python :: 3 :: Only
Requires-Python: >=3.5, <4
